<Woonadressen>
  <Woonadres>
    <woonadresID>1</woonadresID>
    <straatnaam>weilaan</straatnaam>
    <straatnummer>18</straatnummer>
    <postcode>1234AB</postcode>
    <plaats>Weiland</plaats>
  </Woonadres>
  <Woonadres>
    <woonadresID>2</woonadresID>
    <straatnaam>weistraat</straatnaam>
    <straatnummer>21</straatnummer>
    <postcode>1234CD</postcode>
    <plaats>Weiland</plaats>
  </Woonadres>
  <Woonadres>
    <woonadresID>3</woonadresID>
    <straatnaam>weiweg</straatnaam>
    <straatnummer>54</straatnummer>
    <postcode>1234EF</postcode>
    <plaats>Weiland</plaats>
  </Woonadres>
</Woonadressen>